wks/__init__.py
wks/cmake.py
wks/command_build.py
wks/command_clean.py
wks/command_cmake.py
wks/command_cmd.py
wks/command_graph.py
wks/command_help.py
wks/command_install.py
wks/command_install_requirements.py
wks/command_pull.py
wks/command_status.py
wks/commands.py
wks/env.py
wks/git.py
wks/main.py
wks/message.py
workspace/__init__.py
workspace/cmake.py
workspace/command_build.py
workspace/command_clean.py
workspace/command_cmake.py
workspace/command_cmd.py
workspace/command_graph.py
workspace/command_help.py
workspace/command_install.py
workspace/command_install_requirements.py
workspace/command_pull.py
workspace/command_status.py
workspace/commands.py
workspace/env.py
workspace/git.py
workspace/message.py
wks-0.4.3.dist-info/METADATA
wks-0.4.3.dist-info/WHEEL
wks-0.4.3.dist-info/entry_points.txt
wks-0.4.3.dist-info/top_level.txt
wks-0.4.3.dist-info/RECORD
