Metadata-Version: 2.1
Name: wks
Version: 0.4.3
Summary: Simple dependencies manager for cmake projects in your workspace
Home-page: https://github.com/rhoban/wks/
Author: Rhoban team
Author-email: team@rhoban.com
License: UNKNOWN
Keywords: wks workspace deps
Platform: UNKNOWN
Requires-Python: >=3.6
Requires-Dist: colorama
Requires-Dist: pyyaml
